<author lang="en">
	<documents>
		<document><![CDATA[@Basstrader New FX forecast at http://bit.ly/9cSNrV , http://bit.ly/acdGcq Please follow me.]]></document>
		<document><![CDATA[@krasivo New FX forecast at http://bit.ly/9cSNrV , http://bit.ly/acdGcq Please follow me.]]></document>
		<document><![CDATA[@tonylinardo New FX forecast at http://bit.ly/9cSNrV , http://bit.ly/acdGcq Please follow me.]]></document>
		<document><![CDATA[@AmazzingFaith New FX forecast at http://bit.ly/9cSNrV , http://bit.ly/acdGcq Please follow me.]]></document>
		<document><![CDATA[@fxbootcamp New FX forecast at http://bit.ly/9cSNrV , http://bit.ly/acdGcq Please follow me.]]></document>
		<document><![CDATA[@TVN_Kevin New FX forecast at http://bit.ly/9cSNrV , http://bit.ly/acdGcq Please follow me.]]></document>
		<document><![CDATA[@idxtrader New FX forecast at http://bit.ly/9cSNrV , http://bit.ly/acdGcq Please follow me.]]></document>
		<document><![CDATA[@freeforexvideo New FX forecast at http://bit.ly/9cSNrV , http://bit.ly/acdGcq Please follow me.]]></document>
		<document><![CDATA[@gc250 New FX forecast at http://bit.ly/9cSNrV , http://bit.ly/acdGcq Please follow me.]]></document>
		<document><![CDATA[@ZEZOO80 New FX forecast at http://bit.ly/9cSNrV , http://bit.ly/acdGcq Please follow me.]]></document>
		<document><![CDATA[@mec2mec New FX forecast at http://bit.ly/9cSNrV , http://bit.ly/acdGcq Please follow me.]]></document>
		<document><![CDATA[@juliegeorge1905 New FX forecast at http://bit.ly/9cSNrV , http://bit.ly/acdGcq Please follow me.]]></document>
		<document><![CDATA[@QL4828 New FX forecast at http://bit.ly/9cSNrV , http://bit.ly/acdGcq Please follow me.]]></document>
		<document><![CDATA[@jetoepel  New FX forecast at http://bit.ly/9cSNrV , http://bit.ly/acdGcq Please follow me.]]></document>
		<document><![CDATA[@retanqulous New FX forecast at http://bit.ly/9cSNrV , http://bit.ly/acdGcq Please follow me.]]></document>
		<document><![CDATA[@stump1200 New FX forecast at http://bit.ly/9cSNrV , http://bit.ly/acdGcq Please follow me.]]></document>
		<document><![CDATA[@TraderCD New FX forecast at http://bit.ly/9cSNrV , http://bit.ly/acdGcq Please follow me.]]></document>
		<document><![CDATA[@trumanssystem  New FX forecast at http://bit.ly/9cSNrV , http://bit.ly/acdGcq Please follow me.]]></document>
		<document><![CDATA[@ashmanz80  New FX forecast at http://bit.ly/9cSNrV , http://bit.ly/acdGcq Please follow me.]]></document>
		<document><![CDATA[@R_KrisKyokushin  New FX forecast at http://bit.ly/9cSNrV , http://bit.ly/acdGcq Please follow me.]]></document>
		<document><![CDATA[@personalme  New FX forecast at http://bit.ly/9cSNrV , http://bit.ly/acdGcq Please follow me.]]></document>
		<document><![CDATA[@Zak1214 New FX forecast at http://bit.ly/9cSNrV , http://bit.ly/acdGcq Please follow me.]]></document>
		<document><![CDATA[@palludrin New FX forecast at http://bit.ly/9cSNrV , http://bit.ly/acdGcq Please follow me.]]></document>
		<document><![CDATA[@yugidreadboi New FX forecast at http://bit.ly/9cSNrV , http://bit.ly/acdGcq Please follow me.]]></document>
		<document><![CDATA[@_TheDean  New FX forecast at http://bit.ly/9cSNrV , http://bit.ly/acdGcq Please follow me.]]></document>
		<document><![CDATA[@mwweil New FX forecast at http://bit.ly/9cSNrV , http://bit.ly/acdGcq Please follow me.]]></document>
		<document><![CDATA[@jtanew New FX forecast at http://bit.ly/9cSNrV , http://bit.ly/acdGcq Please follow me.]]></document>
		<document><![CDATA[@clay2711 New FX forecast at http://bit.ly/9cSNrV , http://bit.ly/acdGcq Please follow me.]]></document>
		<document><![CDATA[@vkligys New FX forecast at http://bit.ly/9cSNrV , http://bit.ly/acdGcq Please follow me.]]></document>
		<document><![CDATA[@richarf4 New FX forecast at http://bit.ly/9cSNrV , http://bit.ly/acdGcq Please follow me]]></document>
		<document><![CDATA[New FX forecast at http://www.fxstreet.com/technical/market-view/the-chartist-analysis/2010-03-11.html. Please follow me.]]></document>
		<document><![CDATA[@booniepepper  New FX forecast at http://bit.ly/9cSNrV , http://bit.ly/acdGcq Please follow me.]]></document>
		<document><![CDATA[via @huffingtonpost: Economy Recovers Under Obama http://huff.to/9BJ8uu]]></document>
		<document><![CDATA[@it99ts New FX forecast at http://www.fxstreet.com/technical/market-view/the-chartist-analysis/2010-03-11.html. Please follow me.]]></document>
		<document><![CDATA[@MoneyMu1tiplier  New FX forecast at http://www.fxstreet.com/technical/market-view/the-chartist-analysis/2010-03-11.html. Please follow me.]]></document>
		<document><![CDATA[@nottikk New FX forecast at http://www.fxstreet.com/technical/market-view/the-chartist-analysis/2010-03-11.html. Please follow me.]]></document>
		<document><![CDATA[@FX_foraliving New FX forecast at http://www.fxstreet.com/technical/market-view/the-chartist-analysis/2010-03-11.html. Please follow me.]]></document>
		<document><![CDATA[@ybenzine1 New FX forecast at http://www.fxstreet.com/technical/market-view/the-chartist-analysis/2010-03-11.html. Please follow me.]]></document>
		<document><![CDATA[@nayan32 New FX forecast at http://www.fxstreet.com/technical/market-view/the-chartist-analysis/2010-03-11.html. Please follow me.]]></document>
		<document><![CDATA[@CustomTrader New FX forecast at http://www.fxstreet.com/technical/market-view/the-chartist-analysis/2010-03-11.html. Please follow me.]]></document>
		<document><![CDATA[@GoddessAnne New FX forecast at http://www.fxstreet.com/technical/market-view/the-chartist-analysis/2010-03-11.html. Please follow me.]]></document>
		<document><![CDATA[@bashir_fx  New FX forecast at http://www.fxstreet.com/technical/market-view/the-chartist-analysis/2010-03-11.html. Please follow me.]]></document>
		<document><![CDATA[@illdian129 New FX forecast at http://www.fxstreet.com/technical/market-view/the-chartist-analysis/2010-03-11.html. Please follow me.]]></document>
		<document><![CDATA[@Wookie68 New FX forecast at http://www.fxstreet.com/technical/market-view/the-chartist-analysis/2010-03-11.html. Please follow me.]]></document>
		<document><![CDATA[@cprao New FX forecast at http://www.fxstreet.com/technical/market-view/the-chartist-analysis/2010-03-11.html. Please follow me.]]></document>
		<document><![CDATA[@bundanara  New FX forecast at http://www.fxstreet.com/technical/market-view/the-chartist-analysis/2010-03-11.html. Please follow me.]]></document>
		<document><![CDATA[@Footballgoal New FX forecast at http://www.fxstreet.com/technical/market-view/the-chartist-analysis/2010-03-11.html. Please follow me.]]></document>
		<document><![CDATA[@AlyssaMiller3D New FX forecast at http://www.fxstreet.com/technical/market-view/the-chartist-analysis/2010-03-11.html. Please follow me.]]></document>
		<document><![CDATA[@austinschwab New FX forecast at http://www.fxstreet.com/technical/market-view/the-chartist-analysis/2010-03-11.html. Please follow me.]]></document>
		<document><![CDATA[@michaelevs  New FX forecast at http://www.fxstreet.com/technical/market-view/the-chartist-analysis/2010-03-11.html. Please follow me.]]></document>
		<document><![CDATA[@Wallstreetrader New FX forecast at http://www.fxstreet.com/technical/market-view/the-chartist-analysis/2010-03-11.html. Please follow me.]]></document>
		<document><![CDATA[@Highrollernyc New FX forecast at http://www.fxstreet.com/technical/market-view/the-chartist-analysis/2010-03-11.html. Please follow me.]]></document>
		<document><![CDATA[@ForexHeadlines  New FX forecast at http://www.fxstreet.com/technical/market-view/the-chartist-analysis/2010-03-11.html. Please follow me.]]></document>
		<document><![CDATA[@daggy73000  New FX forecast at http://www.fxstreet.com/technical/market-view/the-chartist-analysis/2010-03-11.html. Please follow me.]]></document>
		<document><![CDATA[@heshamsenieh New FX forecast at http://www.fxstreet.com/technical/market-view/the-chartist-analysis/2010-03-11.html. Please follow me.]]></document>
		<document><![CDATA[@PearlFoxx  New FX forecast at http://www.fxstreet.com/technical/market-view/the-chartist-analysis/2010-03-11.html. Please follow me.]]></document>
		<document><![CDATA[@stephanusR New FX forecast at http://www.fxstreet.com/technical/market-view/the-chartist-analysis/2010-03-11.html. Please follow me.]]></document>
		<document><![CDATA[@hdpowell22  New FX forecast at http://www.fxstreet.com/technical/market-view/the-chartist-analysis/2010-03-11.html. Please follow me.]]></document>
		<document><![CDATA[@RayMyoLwin New FX forecast at http://www.fxstreet.com/technical/market-view/the-chartist-analysis/2010-03-11.html. Please follow me.]]></document>
		<document><![CDATA[@Chris_Ciaccia  New FX forecast at http://www.fxstreet.com/technical/market-view/the-chartist-analysis/2010-03-11.html. Please follow me.]]></document>
		<document><![CDATA[@sandou7  New FX forecast at http://www.fxstreet.com/technical/market-view/the-chartist-analysis/2010-03-11.html. Please follow me.]]></document>
		<document><![CDATA[@FXTradingGroup New FX forecast at http://www.fxstreet.com/technical/market-view/the-chartist-analysis/2010-03-11.html. Please follow me.]]></document>
		<document><![CDATA[@fkhan150 New FX forecast at http://www.fxstreet.com/technical/market-view/the-chartist-analysis/2010-03-11.html. Please follow me.]]></document>
		<document><![CDATA[@jtang8888 New FX forecast at http://www.fxstreet.com/technical/market-view/the-chartist-analysis/2010-03-11.html. Please follow me.]]></document>
		<document><![CDATA[@akmst10  New FX forecast at http://www.fxstreet.com/technical/market-view/the-chartist-analysis/2010-03-11.html. Please follow me.]]></document>
		<document><![CDATA[@JeffreyLPJ New FX forecast at http://www.fxstreet.com/technical/market-view/the-chartist-analysis/2010-03-11.html. Please follow me.]]></document>
		<document><![CDATA[@graszoden New FX forecast at http://www.fxstreet.com/technical/market-view/the-chartist-analysis/2010-03-11.html. Please follow me.]]></document>
		<document><![CDATA[@RayinRedondo New FX forecast at http://www.fxstreet.com/technical/market-view/the-chartist-analysis/2010-03-11.html. Please follow me.]]></document>
		<document><![CDATA[@pat_555 New FX forecast at http://www.fxstreet.com/technical/market-view/the-chartist-analysis/2010-03-11.html. Please follow me.]]></document>
		<document><![CDATA[@filiprus  New FX forecast at http://www.fxstreet.com/technical/market-view/the-chartist-analysis/2010-03-11.html. Please follow me.]]></document>
		<document><![CDATA[@dburgess52  New FX forecast at http://www.fxstreet.com/technical/market-view/the-chartist-analysis/2010-03-11.html. Please follow me.]]></document>
		<document><![CDATA[@diggindale New FX forecast at http://www.fxstreet.com/technical/market-view/the-chartist-analysis/2010-03-11.html. Please follow me.]]></document>
		<document><![CDATA[New FX forecast at http://www.fxstreet.com/technical/market-view/the-chartist-analysis/2010-03-11.html. Please follow me.]]></document>
		<document><![CDATA[@fxachieve New FX forecast at http://www.fxstreet.com/technical/market-view/the-chartist-analysis/2010-03-11.html. Please follow me.]]></document>
		<document><![CDATA[@la_neurona New FX forecast at http://www.fxstreet.com/technical/market-view/the-chartist-analysis/2010-03-11.html. Please follow me.]]></document>
		<document><![CDATA[@OnlineForexSite  New FX forecast at http://www.fxstreet.com/technical/market-view/the-chartist-analysis/2010-03-11.html. Please follow me.]]></document>
		<document><![CDATA[@moravictor New FX forecast at http://www.fxstreet.com/technical/market-view/the-chartist-analysis/2010-03-11.html. Please follow me.]]></document>
		<document><![CDATA[@leggaliblonde  New FX forecast at http://www.fxstreet.com/technical/market-view/the-chartist-analysis/2010-03-11.html. Please follow me.]]></document>
		<document><![CDATA[@Glianpeh New FX forecast at http://www.fxstreet.com/technical/market-view/the-chartist-analysis/2010-03-11.html. Please follow me.]]></document>
		<document><![CDATA[@oalvi New FX forecast at http://www.fxstreet.com/technical/market-view/the-chartist-analysis/2010-03-11.html. Please follow me.]]></document>
		<document><![CDATA[@TickerTwits New FX forecast at http://www.fxstreet.com/technical/market-view/the-chartist-analysis/2010-03-11.html. Please follow me.]]></document>
		<document><![CDATA[@chinanewsbreak New FX forecast at http://www.fxstreet.com/technical/market-view/the-chartist-analysis/2010-03-11.html. Please follow me.]]></document>
		<document><![CDATA[@Satkumoro New FX forecast at http://www.fxstreet.com/technical/market-view/the-chartist-analysis/2010-03-11.html. Please follow me.]]></document>
		<document><![CDATA[@haptrade New FX forecast at http://www.fxstreet.com/technical/market-view/the-chartist-analysis/2010-03-11.html. Please follow me.]]></document>
		<document><![CDATA[@theforexgal New FX forecast at http://www.fxstreet.com/technical/market-view/the-chartist-analysis/2010-03-11.html. Please follow me.]]></document>
		<document><![CDATA[@DiegoGomezsp New FX forecast at http://www.fxstreet.com/technical/market-view/the-chartist-analysis/2010-03-11.html. Please follow me.]]></document>
		<document><![CDATA[@Edmundfriends New FX forecast at http://www.fxstreet.com/technical/market-view/the-chartist-analysis/2010-03-11.html. Please follow me.]]></document>
		<document><![CDATA[@sedakensearch New FX forecast at http://www.fxstreet.com/technical/market-view/the-chartist-analysis/2010-03-11.html. Please follow me.]]></document>
		<document><![CDATA[@Blakebousa New FX forecast at http://www.fxstreet.com/technical/market-view/the-chartist-analysis/2010-03-11.html. Please follow me.]]></document>
		<document><![CDATA[@wizardkao New FX forecast at http://www.fxstreet.com/technical/market-view/the-chartist-analysis/2010-03-11.html. Please follow me.]]></document>
		<document><![CDATA[@pk4412 New FX forecast at http://www.fxstreet.com/technical/market-view/the-chartist-analysis/2010-03-11.html. Please follow me.]]></document>
		<document><![CDATA[@alkomety New FX forecast at http://www.fxstreet.com/technical/market-view/the-chartist-analysis/2010-03-11.html. Please follow me.]]></document>
		<document><![CDATA[@tarans01 New FX forecast @ http://twitter.com/daniel_bruno please follow my business partner and we will follow you!]]></document>
		<document><![CDATA[@iventertain New FX forecast at http://www.fxstreet.com/technical/market-view/the-chartist-analysis/2010-03-11.html. Please follow me.]]></document>
		<document><![CDATA[@aaprivate  New FX forecast at http://www.fxstreet.com/technical/market-view/the-chartist-analysis/2010-03-11.html. Please follow me.]]></document>
		<document><![CDATA[@HaseenaBegum New FX forecast at http://www.fxstreet.com/technical/market-view/the-chartist-analysis/2010-03-11.html. Please follow me.]]></document>
		<document><![CDATA[@kevincmull New FX forecast at http://www.fxstreet.com/technical/market-view/the-chartist-analysis/2010-03-11.html. Please follow me.]]></document>
		<document><![CDATA[@khiranoooo New FX forecast at http://www.fxstreet.com/technical/market-view/the-chartist-analysis/2010-03-11.html. Please follow me.]]></document>
		<document><![CDATA[@nasiripour New FX forecast at http://www.fxstreet.com/technical/market-view/the-chartist-analysis/2010-03-11.html. Please follow me.]]></document>
		<document><![CDATA[@RichardBDarling New FX forecast at http://www.fxstreet.com/technical/market-view/the-chartist-analysis/2010-03-11.html. Please follow me.]]></document>
	</documents>
</author>