<author lang="en">
	<documents>
		<document><![CDATA[$BRK.B - Berkshire Hathaway Stock Analysis - CCI is bullish - http://t.co/yxJOWsjL http://t.co/6cwDkvP9]]></document>
		<document><![CDATA[Is Warren Being Very Un-Buffett? (BRK-B, IBM) http://t.co/3SkMmMCP http://t.co/4znP0La3]]></document>
		<document><![CDATA[$BRK.B - Berkshire Hathaway Stock Analysis - bullish stochastic crossover - http://t.co/z8B7sPW4 http://t.co/ddWKzQ1O]]></document>
		<document><![CDATA[Is Warren Being Very Un-Buffett? (BRK-B, IBM) http://t.co/3SkMmMCP http://t.co/9wNOhB0P]]></document>
		<document><![CDATA[Commented on: "Fairholme's Major Transactions For Q3 2011" http://t.co/plnRKQkn $MS $GS $AIG $C $RF $BAC $BRK.A ... http://t.co/xf5WK5Ij]]></document>
		<document><![CDATA[$BRK.B - Berkshire Hathaway Stock Analysis - bullish stochastic crossover - http://t.co/yxJOWsjL http://t.co/ebf2zjM1]]></document>
		<document><![CDATA[Berkshire's NetJets Sues IRS http://t.co/ecwRO26e via @WSJ $BRK.B  you ahve to pay your fair share! come on now! http://t.co/u1XI3Uhh]]></document>
		<document><![CDATA[RT @BRK_B: 4 Stocks abt as Cheap as They've evr bn (AAPL, BRK-B, HPQ, WFC, WMT) http://t.co/5ej0VRoY htt... http://t.co/HveL5EVY]]></document>
		<document><![CDATA[$BRK.B - Berkshire Hathaway Stock Analysis - bullish stochastic crossover - http://t.co/yxJOWsjL http://t.co/3bILTpTn]]></document>
		<document><![CDATA[Guy u go get hrt brk b datRT @vanheusen_2: @fugeeflames; how na bros? Who wan clear these doubts? Morrison? All ... http://t.co/m74Op8nZ]]></document>
		<document><![CDATA[4 Stocks About as Cheap as They've Ever Been (AAPL, BRK-B, HPQ, WFC, WMT) http://t.co/3xOFKgzz http://t.co/O4fGrhz4]]></document>
		<document><![CDATA[4 Stocks About as Cheap as They've Ever Been (AAPL, BRK-B, HPQ, WFC, WMT) http://t.co/3xOFKgzz http://t.co/9BKJmd5Y]]></document>
		<document><![CDATA[$BRK.B - Berkshire Hathaway Stock Analysis - volume up over 10% - http://t.co/yxJOWsjL http://t.co/3dBOCeDs]]></document>
		<document><![CDATA[RT @BRK_B: 4 Stocks About as Cheap as They've Ever Been $AAPL $BRK-B $HPQ  $WFC  $WMT http://t.co/3xOFKgzz http:... http://t.co/yVDoHp96]]></document>
		<document><![CDATA[$BRK.B - Berkshire Hathaway Stock Analysis - bullish stochastic crossover - http://t.co/z8B7sPW4 http://t.co/HywebWKu]]></document>
		<document><![CDATA[Todd Combs's Q3 Acquisitions For Berkshire http://t.co/fIhjd6R5 $CVS $DTV $INTC $GD $V $DG $IBM $BRK.A $BRK.B http://t.co/GVwV75Sx]]></document>
		<document><![CDATA[4 Stocks About as Cheap as They've Ever Been $AAPL $BRK-B $HPQ  $WFC  $WMT http://t.co/3xOFKgzz http://t.co/XPw8cixE]]></document>
		<document><![CDATA[RT @Wisedom $AAPL & $AMZN not looking pretty. Like the look of $BRK though... $BRK.B that should be http://t.co/fzKfQQnr]]></document>
		<document><![CDATA[3 Things to Remember About Buffett's Buying Spree (BRK-B) http://t.co/5Ub2Aa0i http://t.co/782iZh4A]]></document>
		<document><![CDATA[RT @BRK_B: 5 Financial #Stocks #Hedge Funds Are Buying http://t.co/ZfJVW2m9 $BRK.B $USB $CMA http://t.co/xsyOred0 http://t.co/1Z9LCrKv]]></document>
		<document><![CDATA[5 Financial #Stocks #Hedge Funds Are Buying http://t.co/ZfJVW2m9 $BRK.B $USB $CMA http://t.co/xsyOred0]]></document>
		<document><![CDATA[Commented on: "Fairholme's Major Transactions For Q3 2011" http://t.co/plnRKQkn $MS $GS $AIG $C $RF $BAC $BRK.A ... http://t.co/pkfPaqEk]]></document>
		<document><![CDATA[BRK b ....bull trend. http://t.co/Mb8tnoxM]]></document>
		<document><![CDATA[RT @StocksMD: RT @valuewalk: Whitney Tilson October 2011 Shareholder Letter  http://t.co/M1IQnizY $C $BRK-A $BRK... http://t.co/TWraVxiU]]></document>
		<document><![CDATA[@chrisspinell When to buy $BRK-B? http://t.co/9hNvQt6M]]></document>
		<document><![CDATA[RT @valuewalk: Whitney Tilson October 2011 Shareholder Letter  http://t.co/M1IQnizY $C $BRK-A $BRK-B $JCP $HHC $... http://t.co/81A9Khfn]]></document>
		<document><![CDATA[HP's New Winning Strategy: Earning Money Faster Than It Spends It http://t.co/RLKZ4oSD $HPQ $IBM $DELL $BRK.B http://t.co/exSqnScy]]></document>
		<document><![CDATA[$BRK.B - Berkshire Hathaway Stock Analysis - 10day moving average is down - http://t.co/yxJOWsjL http://t.co/mXvU5TtZ]]></document>
		<document><![CDATA[Whitney Tilson October 2011 Shareholder Letter  http://t.co/M1IQnizY $C $BRK-A $BRK-B $JCP $HHC $NFLX $GMCR $CRM http://t.co/tbfgVBBf]]></document>
		<document><![CDATA[$BRK.B - Berkshire Hathaway Stock Analysis - CCI is bullish and rising - http://t.co/z8B7sPW4 http://t.co/mc1JareL]]></document>
		<document><![CDATA[$BRK.B - Berkshire Hathaway Stock Analysis - CCI is bullish and rising - http://t.co/z8B7sPW4 http://t.co/mr5F5mbZ]]></document>
		<document><![CDATA[Looking to start accumulating again. $C, $WFC, $BRK-B, $NKE, $MSFT, $GE and some others on my radar. http://t.co/oX8rAO7c]]></document>
		<document><![CDATA[PEP, NYB, CTL, WY, BRK. B - Notable Stocks with Volume at NYSE - Retirement Planning http://t.co/3J2LGJV9]]></document>
		<document><![CDATA[IBM: Good Company at Fair Price?: $IBM, $BRK.A, $BRK.B, $AAPL, $INTC, $MSFT http://t.co/fWtVRlO6 http://t.co/7HRLyHlo]]></document>
		<document><![CDATA[Love the emails with buy recs for Berkshire Hathaway. Really? Find an actual limb to go out on... $BRK-A $BRK-B http://t.co/LFly1f2a]]></document>
		<document><![CDATA[@alia1977 @Wahab_m_alfares brk-b http://t.co/Aj0MAyVI]]></document>
		<document><![CDATA[Commented on: "Fairholme's Major Transactions For Q3 2011" http://t.co/plnRKQkn $MS $GS $AIG $C $RF $BAC $BRK.A ... http://t.co/xM5qABrX]]></document>
		<document><![CDATA[Chuck Akre Buys BRK.B, MKL, BAC, HIG, AAPL, Sells ARO, WMS, AGO, XOM: $BRK. ... http://t.co/wJurodca http://t.co/oDMgGAFf]]></document>
		<document><![CDATA[$BRK.B - Berkshire Hathaway Stock Analysis - bearish stochastic crossdown - http://t.co/yxJOWsjL http://t.co/JMnJregR]]></document>
		<document><![CDATA[What the Smart Investors Are Up To (AA, AAPL, BAC, BRK-B, HPQ, IBM, MGM) http://t.co/7ud66eFr http://t.co/GgiX5f3J]]></document>
		<document><![CDATA[Burlington Northern Santa Fe $BRK-A plans to spend $700M on developing terminals  http://t.co/aefz7n6Y $BRK-B http://t.co/h2Zqh0Dz]]></document>
		<document><![CDATA[BCS, BRK/B, AUY, FII, EK  Stocks to watch at NYSE ;O http://t.co/BjSftemi online business card printing http://t.co/bUAdI8WF]]></document>
		<document><![CDATA[5 Buys Bill Gates Sees Upside In Now http://t.co/v6oMIUvL $BRK.B $CX $CMCSK $KO $LZ $AAPL http://t.co/roWKOnVf]]></document>
		<document><![CDATA[$BRK.B - Berkshire Hathaway Stock Analysis - volume up over 10% - http://t.co/yxJOWsjL http://t.co/gPvZYjku]]></document>
		<document><![CDATA[$BRK.B - Berkshire Hathaway Stock Analysis - bearish stochastic crossdown - http://t.co/z8B7sPW4 http://t.co/8SYIU99C]]></document>
		<document><![CDATA[Berkshire Hathaway Inc (BRK.B): Today's Featured Insurance Loser - http://t.co/itkrtCHi http://t.co/MyLQ5hMo http://t.co/vCCyTVUl]]></document>
		<document><![CDATA[$BRK.B - Berkshire Hathaway Stock Analysis - bearish stochastic crossdown - http://t.co/z8B7sPW4 http://t.co/RNxJInKZ]]></document>
		<document><![CDATA[What the Smart Investors Are Up To (AA, AAPL, BAC, BRK-B, HPQ, IBM, MGM) http://t.co/7ud66eFr http://t.co/WUeI7M2t]]></document>
		<document><![CDATA[$BRK.B - Berkshire Hathaway Stock Analysis - volume up over 10% - http://t.co/z8B7sPW4 http://t.co/zOxrp7gJ]]></document>
		<document><![CDATA[BCS, BRK/B, AUY, FII, EK - Stocks to watch at NYSE - Retirement Planning http://t.co/Bz400wf1]]></document>
		<document><![CDATA[RT @BRK_B: If $AAPL gets down to $380 I will start to build a position. Also looking into building a position in... http://t.co/1EcJm50F]]></document>
		<document><![CDATA[If $AAPL gets down to $380 I will start to build a position. Also looking into building a position in $brk.b and $L.to http://t.co/oT0uBdSH]]></document>
		<document><![CDATA[RT @WallStWatchDog: Southeastern Asset Management is Bullish on These Stocks for Q3 2011 http://t.co/hda4OAl0 #B... http://t.co/WwTOU6XW]]></document>
		<document><![CDATA[Southeastern Asset Manage is Bearish on These Stocks for Q3 2011 http://t.co/m6dv56KV #BRK.B $VOD #nwsa $FICO $I... http://t.co/ThU18nG0]]></document>
		<document><![CDATA[Southeastern Asset Management is Bullish on These Stocks for Q3 2011 http://t.co/hda4OAl0 #BRK.B $IR $KWK $SKS $SNI http://t.co/WhUHQiKZ]]></document>
		<document><![CDATA[RT @SeekingAlpha: Vanguard Founder John Bogle's Outlook For The New Year http://t.co/4Qasyk1K $CL $KO $PG $PEP $... http://t.co/H4fvfwPT]]></document>
		<document><![CDATA[Vanguard Founder John Bogle's Outlook For The New Year http://t.co/4Qasyk1K $CL $KO $PG $PEP $JNJ $BRK.A $BRK.B http://t.co/TDEtLD2g]]></document>
		<document><![CDATA[My worst investment decision of the year was Brk-B, no yield, no gains, no love http://t.co/Wo7CzVbS]]></document>
		<document><![CDATA[Charlie Munger: Art of Stock Picking: BRK.A, BRK.B http://t.co/bE2CNfZi]]></document>
		<document><![CDATA[How To Profit From The Return Of The Credit Card http://t.co/ArcR0ZEw $V $MA $DFS $AXP $BRK.A $BRK.B http://t.co/9vZPTdEJ]]></document>
		<document><![CDATA[Charlie Munger: Art of Stock Picking: BRK.A, BRK.B http://t.co/xCC3x5w5]]></document>
		<document><![CDATA[Buffett On Loser List: Marketwatch Misrepresents Berkshire Hathaway http://t.co/2jigrJnh $BAC $GS $GE $JNJ $IBM ... http://t.co/xftup08V]]></document>
		<document><![CDATA[Charlie Munger: Art of Stock Picking: BRK.A, BRK.B http://t.co/6TEwr5Yu http://t.co/6wwwRjzm]]></document>
		<document><![CDATA[$BRK.B - Berkshire Hathaway Stock Analysis - 5day ema crossover - http://t.co/z8B7sPW4 http://t.co/beuenmFF]]></document>
		<document><![CDATA[Charlie Munger: Art of Stock Picking: BRK.A, BRK.B http://t.co/6kdG1wXA]]></document>
		<document><![CDATA[Charlie Munger: Art of Stock Picking: BRK.A, BRK.B http://t.co/xkI28BYj]]></document>
		<document><![CDATA[$BRK.B - Berkshire Hathaway Stock Analysis - Last Engulfing Top Candlestick Pattern - http://t.co/yxJOWsjL http://t.co/YaR6uQv3]]></document>
		<document><![CDATA[$BRK.B - Berkshire Hathaway Stock Analysis - Last Engulfing Top Candlestick Pattern - http://t.co/yxJOWsjL http://t.co/qqlvV6rl]]></document>
		<document><![CDATA[Buffett Compunding $1 Mil. and Why Should an Investor Learn Austrian Economics http://t.co/29jIRHdy $$ $BRK-A $BRK-B http://t.co/PivHrP57]]></document>
		<document><![CDATA[RT @BRK_B: #Apple, @Google, Berkshire: The Stocks Investors Want for Christmas http://t.co/UnO01zlH $AAPL $GOOG ... http://t.co/WYertu1d]]></document>
		<document><![CDATA[RT @BRK_B: #Apple, @Google, Berkshire: The Stocks Investors Want for Christmas http://t.co/UnO01zlH $AAPL $GOOG ... http://t.co/WfdZytjA]]></document>
		<document><![CDATA[$BRK.B - Berkshire Hathaway Stock Analysis - price & sma crossover, #bull stock - http://t.co/yxJOWsjL http://t.co/qFNFTgNb]]></document>
		<document><![CDATA[RT @BRK_B: #Apple, @Google, Berkshire: The Stocks Investors Want for Christmas http://t.co/UnO01zlH $AAPL $GOOG ... http://t.co/4ufi4klW]]></document>
		<document><![CDATA[RT @BRK_B: #Apple, @Google, Berkshire: The Stocks Investors Want for Christmas http://t.co/UnO01zlH $AAPL $GOOG ... http://t.co/vtzSFjAP]]></document>
		<document><![CDATA[RT @BRK_B: #Apple, @Google, Berkshire: The Stocks Investors Want for Christmas http://t.co/UnO01zlH $AAPL $GOOG ... http://t.co/ybAueMuG]]></document>
		<document><![CDATA[RT @BRK_B: #Apple, @Google, Berkshire: The Stocks Investors Want for Christmas http://t.co/UnO01zlH $AAPL $GOOG ... http://t.co/MiM8dDSS]]></document>
		<document><![CDATA[RT @BRK_B: #Apple, @Google, Berkshire: The Stocks Investors Want for Christmas http://t.co/UnO01zlH $AAPL $GOOG ... http://t.co/YWH6eeoL]]></document>
		<document><![CDATA[Top Financial Stocks Hedge Fund Gurus Bought: WFC, BRK.B, V, BK http://t.co/bf7NAnZu]]></document>
		<document><![CDATA[$BRK.B - Berkshire Hathaway Stock Analysis - bullish macd crossover, #bull signal - http://t.co/yxJOWsjL http://t.co/oSpY0iU2]]></document>
		<document><![CDATA[RT @BRK_B: #Apple, @Google, Berkshire: The Stocks Investors Want for Christmas http://t.co/UnO01zlH $AAPL $GOOG ... http://t.co/XUmLtKQq]]></document>
		<document><![CDATA[RT @BRK_B: #Apple, @Google, Berkshire: The Stocks Investors Want for Christmas http://t.co/UnO01zlH $AAPL $GOOG ... http://t.co/nyYxWEWR]]></document>
		<document><![CDATA[RT @BRK_B: #Apple, @Google, Berkshire: The Stocks Investors Want for Christmas http://t.co/UnO01zlH $AAPL $GOOG ... http://t.co/NxuTgJRY]]></document>
		<document><![CDATA[RT @BRK_B: #Apple, @Google, Berkshire: The Stocks Investors Want for Christmas http://t.co/UnO01zlH $AAPL $GOOG ... http://t.co/dhy5rlDw]]></document>
		<document><![CDATA[@KeithMcCullough @HedgeyeSnakeye makes sense with the coming crude sell off Happy Holidays -GO BRK.B lol http://t.co/v2fOFFyF]]></document>
		<document><![CDATA[RT @BRK_B: #Apple, @Google, Berkshire: The Stocks Investors Want for Christmas http://t.co/UnO01zlH $AAPL $GOOG ... http://t.co/i3okgaXx]]></document>
		<document><![CDATA[RT @BRK_B: #Apple, @Google, Berkshire: The Stocks Investors Want for Christmas http://t.co/UnO01zlH $AAPL $GOOG ... http://t.co/36JV8NG6]]></document>
		<document><![CDATA[General Electric: A Historically Cheap Stock To Buy Today http://t.co/Iaw0hIhT $GE $BRK.A $BRK.B $CMCSA http://t.co/suuSgEdN]]></document>
		<document><![CDATA[RT @BRK_B: #Apple, @Google, Berkshire: The Stocks Investors Want for Christmas http://t.co/UnO01zlH $AAPL $GOOG ... http://t.co/O2zISGyA]]></document>
		<document><![CDATA[RT @BRK_B: #Apple, @Google, Berkshire: The Stocks Investors Want for Christmas http://t.co/UnO01zlH $AAPL $GOOG ... http://t.co/FnJJj5Ik]]></document>
		<document><![CDATA[RT @BRK_B: #Apple, @Google, Berkshire: The Stocks Investors Want for Christmas http://t.co/UnO01zlH $AAPL $GOOG ... http://t.co/nXaAYfcn]]></document>
		<document><![CDATA[$BRK.B - Berkshire Hathaway Stock Analysis - volume down over 5% - http://t.co/yxJOWsjL http://t.co/IV47Ub8c]]></document>
		<document><![CDATA[#Apple, @Google, Berkshire: The Stocks Investors Want for Christmas http://t.co/0CullDdp $AAPL $GOOG $BRK.B http://t.co/RiyTmZm5]]></document>
		<document><![CDATA[RT @BRK_B: #Apple, @Google, Berkshire: The Stocks Investors Want for Christmas http://t.co/UnO01zlH $AAPL $GOOG ... http://t.co/hQ6L3aLe]]></document>
		<document><![CDATA[RT @BRK_B: #Apple, @Google, Berkshire: The Stocks Investors Want for Christmas http://t.co/UnO01zlH $AAPL $GOOG ... http://t.co/T2AYJ7Tp]]></document>
		<document><![CDATA[RT @BRK_B: #Apple, @Google, Berkshire: The Stocks Investors Want for Christmas http://t.co/UnO01zlH $AAPL $GOOG ... http://t.co/C5kFPM0l]]></document>
		<document><![CDATA[RT @BRK_B: #Apple, @Google, Berkshire: The Stocks Investors Want for Christmas http://t.co/UnO01zlH $AAPL $GOOG ... http://t.co/jDRHPQ9d]]></document>
		<document><![CDATA[$BRK.B - Berkshire Hathaway Stock Analysis - bullish macd crossover - http://t.co/z8B7sPW4 http://t.co/cKZDfaoh]]></document>
		<document><![CDATA[RT @BRK_B: #Apple, @Google, Berkshire: The Stocks Investors Want for Christmas http://t.co/UnO01zlH $AAPL $GOOG ... http://t.co/dySVDSs0]]></document>
		<document><![CDATA[RT @BRK_B: #Apple, @Google, Berkshire: The Stocks Investors Want for Christmas http://t.co/UnO01zlH $AAPL $GOOG ... http://t.co/1H7VAI2g]]></document>
		<document><![CDATA[RT @BRK_B: #Apple, @Google, Berkshire: The Stocks Investors Want for Christmas http://t.co/UnO01zlH $AAPL $GOOG ... http://t.co/4kGf5VM0]]></document>
	</documents>
</author>