<author lang="es">
	<documents>
		<document><![CDATA[#wg Un coloso musical llamado Stevie Wonder - A estas alturas de siglo XXI, se dice poco: Stevie Wonder es un g... https://t.co/koJMhRPWPq]]></document>
		<document><![CDATA[#wg Los jueces piden que Madrid devuelva las competencias en Justicia https://t.co/fEpfaPzIVr]]></document>
		<document><![CDATA[#wg Un profesor de Vigo descubre un manuscrito en gallego en plenos Séculos Escuros https://t.co/9ftNSTee9x]]></document>
		<document><![CDATA[#wg Prisión para el supuesto fratricida de Guadarrama - La titular del juzgado de instrucción número 4 de Colla... https://t.co/TTDvxbT1Rj]]></document>
		<document><![CDATA[#wg Los abogados a los que China teme casi tanto como a Liu Xiaobo https://t.co/g4kDgCBHk4]]></document>
		<document><![CDATA[#wg 200 afiliados de Catalunya en Comu firman un manifiesto contra el 1-O https://t.co/IziIPlR4sO]]></document>
		<document><![CDATA[#wg Sentada universitaria hasta que los reciba Méndez de Vigo para hablar de becas https://t.co/bGpkN6hT1g]]></document>
		<document><![CDATA[#wg Hamilton logra la pole en Silverstone y Alonso saldrá el último https://t.co/C39FxbPBZB]]></document>
		<document><![CDATA[#wg Garbiñe Muguruza desdibuja a Venus Williams y conquista Wimbledon https://t.co/zzOspcyIAB]]></document>
		<document><![CDATA[#wg GP de Gran Bretaña en Silverstone de F1 2017: horario y dónde ver la carrera en vivo y en directo https://t.co/40xfJZXwE3]]></document>
		<document><![CDATA[#wg Cinco prescripciones para la salud global - Los detalles de los datos recogidos en el último informe de seg... https://t.co/PgS3iG4O6V]]></document>
		<document><![CDATA[#wg Un año del golpe de Estado en Turquía - El Gobierno islamista de Turquía ultima los preparativos para conme... https://t.co/DfHiTJeCHs]]></document>
		<document><![CDATA[#wg La final de Wimbledon 2017, en imágenes - La tenista española, de 23 años, disputa la final del grande brit... https://t.co/lXwboYTnOa]]></document>
		<document><![CDATA[#wg Cinco lecturas para esta tarde de sábado - El infierno de la niña Naiara en la casa de los horrores Seguir ... https://t.co/wdxpPXaMlF]]></document>
		<document><![CDATA[#wg ¿De verdad ‘Despacito’ ha disparado un 45% el turismo en Puerto Rico? https://t.co/vm3UGMyb6E]]></document>
		<document><![CDATA[#wg ¿Qué ver hoy en TV? | Sábado 15 de julio - 15.00 / 0# Seguir leyendo. https://t.co/6bxaGFLn8Q]]></document>
		<document><![CDATA[#wg Muguruza – Venus Williams en directo, la final de Wimbledon 2017 en vivo https://t.co/T0t9mHvmBG]]></document>
		<document><![CDATA[#wg GP de Gran Bretaña de F1 en Silverstone, la clasificación en vivo y en directo https://t.co/RBc30XD5MN]]></document>
		<document><![CDATA[#wg Rajoy anima a Puigdemont a seguir el ejemplo de Euskadi - El presidente del Gobierno, Mariano Rajoy, ha int... https://t.co/2mRRsVicur]]></document>
		<document><![CDATA[#wg La laringe "incorrupta" de Gayarre - He tenido la recentísima experiencia de contemplar la laringe "incorru... https://t.co/BmNuXdgh0l]]></document>
		<document><![CDATA[#wg Puigdemont vuela el último puente - “Es un equipo de hooligans, sin distinciones”, insiste la misma fuente ... https://t.co/1Or00c96jk]]></document>
		<document><![CDATA[#wg México contra… ¿Curazao? - Eloy Room, Leandro Bacuna, Jarchinio Antonio, Gevaro Nepomuceno… Muchos de estos... https://t.co/gljWRf8wfW]]></document>
		<document><![CDATA[#wg El aventurero que encontró un tesoro en las montañas de Los Andes https://t.co/aNgOx05VsD]]></document>
		<document><![CDATA[#wg Brasil, el país en el que los jueces tomaron el poder - El vaso se ha colmado en las últimas dos semanas, m... https://t.co/9FOIx3OUA5]]></document>
		<document><![CDATA[#wg El riesgo de tener un accidente en bicicleta es menor que en coche https://t.co/QVS27fo7kJ]]></document>
		<document><![CDATA[#wg La tasa de ahorro de las familias cae a la mitad del nivel que alcanzó en 2009 https://t.co/qndIrQ2FKW]]></document>
		<document><![CDATA[#wg Ona Carbonell, la última superviviente - Las autobiografías deportivas, como casi todas las autobiografías,... https://t.co/xgEKy2MjB4]]></document>
		<document><![CDATA[#wg Sant Feliu de Guíxols tendrá la obra catalana de la Thyssen en 2020 https://t.co/WIfPz7wXnG]]></document>
		<document><![CDATA[#wg La playa más popular de Fukushima, reabierta siete años después del accidente nuclear https://t.co/HagQUUs0O6]]></document>
		<document><![CDATA[#wg La defensa apasionada del medio ambiente del gobernador de California https://t.co/yo2ofV1A0l]]></document>
		<document><![CDATA[#wg Un retorno inesperado: Froome recupera el amarillo en una cuestecita https://t.co/afpuuarzfG]]></document>
		<document><![CDATA[#wg La presencia de milicias chiíes cerca de Mosul irrita a suníes y kurdos https://t.co/WY6F89USup]]></document>
		<document><![CDATA[#wg Sánchez pide a Rajoy que negocie con Puigdemont para evitar el referéndum https://t.co/AH2lCiYiBl]]></document>
		<document><![CDATA[#wg Fujimori y Humala, presos. Toledo, acusado. ¿Qué pasa en el Perú? https://t.co/A2xShTm3CP]]></document>
		<document><![CDATA[#wg ¿Estás listo para la séptima temporada de ‘Juego de Tronos’? https://t.co/yKw9HMgrkN]]></document>
		<document><![CDATA[#wg Lula: el derrumbe del político más carismático del mundo https://t.co/NP2jDiOFs8]]></document>
		<document><![CDATA[#wg Las 5 mejores aerolíneas para viajar con niños - Cuando te conviertes en padre cambian muchas cosas en tu v... https://t.co/8O9kR00UiG]]></document>
		<document><![CDATA[#wg Bañador, crema solar… y cinco ‘apps’ para cuidar de tu dinero en vacaciones https://t.co/176ZEQIRAm]]></document>
		<document><![CDATA[#wg Hay una parte de ti que lucha contra la igualdad - Los seres humanos muestran una aversión generalizada a l... https://t.co/x40UA7mZdu]]></document>
		<document><![CDATA[#wg Los cristianos de Irak aún temen volver a sus pueblos - “La gente tiene miedo de volver”. Así de contundent... https://t.co/kWkntysPYp]]></document>
		<document><![CDATA[#wg 14 personajes de ‘Juego de tronos’ que no nos explicamos cómo siguen vivos https://t.co/tvurtvEmqK]]></document>
		<document><![CDATA[#wg Kuczynski sobre la detención de Humala: "Es muy triste lo que está pasando" https://t.co/yAtAf63z3W]]></document>
		<document><![CDATA[#wg Los cultivos de coca en Colombia aumentaron más del 50% en 2016 https://t.co/LqeG0Diyph]]></document>
		<document><![CDATA[#wg Castro acusa a Trump de “recrudecer el cerco unilateral” a Cuba https://t.co/UNodGHT2p7]]></document>
		<document><![CDATA[#wg La anorexia, plano a plano - Dicen que el cine es reflejo de la sociedad. La anorexia y los trastornos alim... https://t.co/9HlcTvZx5U]]></document>
		<document><![CDATA[#wg Migración pendular, asesinatos y aftosa - La conocida como frontera caliente desde las épocas del diferendo... https://t.co/x0Yqgb9kHR]]></document>
		<document><![CDATA[#wg El Río Santiago, el río de la muerte en Jalisco - La organización civil Un salto por la vida ha organizado ... https://t.co/whvhU5FjCU]]></document>
		<document><![CDATA[#wg El peronismo dividido abre la campaña electoral en Argentina https://t.co/o3mZklqiMt]]></document>
		<document><![CDATA[#wg “Los chilenos no quieren refundar el país, sino cambio con estabilidad” https://t.co/TKPbajUi46]]></document>
		<document><![CDATA[#wg 10 Estados mexicanos buscan amparar a los ciudadanos que maten en defensa propia https://t.co/iMfBXRT3Wj]]></document>
		<document><![CDATA[#wg El extraño viaje de un Greco mexicano - “A los santos les corresponde peregrinar”, dice Alfredo Robert en e... https://t.co/7JHtH4sOLq]]></document>
		<document><![CDATA[#wg Demagogia judicial - En algún momento de la ultramaratónica sesión judicial que terminó con la sentencia de... https://t.co/Bl0L2mSP43]]></document>
		<document><![CDATA[#wg “Hablar de la Transición como régimen del 78 es despectivo” https://t.co/talxQznCrj]]></document>
		<document><![CDATA[#wg Miedo en Cataluña - Hay miedo en Cataluña. Pero no un miedo general ciudadano, aunque a medida que se radic... https://t.co/8fAt4hRGKe]]></document>
		<document><![CDATA[#wg El renacimiento de Céline Dion - Influencers, blogueros e it girls han tenido este año una competidora dura... https://t.co/axAmW7uPQs]]></document>
		<document><![CDATA[#wg ...Y ahora la letanía de la ‘turismofobia’ - Durante décadas el turismo ha estado en la base del crecimient... https://t.co/nXR9EcEVRx]]></document>
		<document><![CDATA[#wg El 14 de julio - Ese 14 de julio de 1789 no era un martes cualquiera; tampoco una rebelión, como pensaba Lu... https://t.co/SrWMxCMr7d]]></document>
		<document><![CDATA[#wg Forges - Viñeta de Forges del 15 de julio de 2017 https://t.co/HZRTfYhhSJ]]></document>
		<document><![CDATA[#wg El Mundial de Budapest amenaza la supremacía de Estados Unidos https://t.co/6nNFvWjixY]]></document>
		<document><![CDATA[#wg La aglomeración - Todo lleno titulaba Manuel Vicent su columna del domingo pasado. Efectivamente, como efec... https://t.co/W9ObQczoUn]]></document>
		<document><![CDATA[#wg Michael Connelly: “Mucho policía busca hoy la seguridad del despacho” https://t.co/A6ayw0GIne]]></document>
		<document><![CDATA[#wg Chet Baker, poeta de la derrota - Chet Baker siempre cantó, incluso cuando se estableció como el gran tromp... https://t.co/syNofQSx3C]]></document>
		<document><![CDATA[#wg Puerta grande para un dolorido Rafaelillo - Sin chaquetilla ni chaleco, con los tirantes rotos y hecho un m... https://t.co/y3mTE2tWKf]]></document>
		<document><![CDATA[#wg Beyoncé presenta a sus mellizos vestida de Palomo Spain - Beyoncé, de 35 años, ha hecho pública la primera ... https://t.co/dC1CVXVKO4]]></document>
		<document><![CDATA[#wg El nuevo Gobierno de Puigdemont, en directo - El presidente de la Generalitat, Carles Puigdemont, detallará... https://t.co/uc19X4xzvj]]></document>
		<document><![CDATA[#wg GP de Silverstone 2017: horario y dónde ver MotoGP en vivo y en directo https://t.co/BL1H3NqoIr]]></document>
		<document><![CDATA[#wg Jordi Turull y Joaquim Forn se perfilan como nuevos consejeros de Puigdemont https://t.co/He5o1Ony2m]]></document>
		<document><![CDATA[#wg Octavo encierro de San Fermín, en imágenes - Pamplona vive el octavo y último día de las fiestas de San Fer... https://t.co/C4kpD8S0yO]]></document>
		<document><![CDATA[#wg Madre actual: taxista no remunerada y secretaria a tiempo completo https://t.co/in6A8Qlqpp]]></document>
		<document><![CDATA[#wg Este chico tatúa las escenas de tus pelis favoritas - Desde su cuenta de Instagram '@pigmentninja', Alican ... https://t.co/qLmzx2AjKp]]></document>
		<document><![CDATA[#wg Ya está bien - Después de cuarenta años y medio de dedicación exclusiva a la vida universitaria, y en concr... https://t.co/4vnR8XrXcp]]></document>
		<document><![CDATA[#wg Así será la primera atracción basada en Star Wars que estrenará Disneyland https://t.co/Kj5CEG5IzL]]></document>
		<document><![CDATA[#wg Las cinco noticias clave del 14 de julio - El PSOE y el PSC defienden el reconocimiento de "la aspiración n... https://t.co/yrYUUI9vrl]]></document>
		<document><![CDATA[#wg “El ISIS dispara a los civiles que intentan escapar” - “Nos fuimos por los bombardeos y porque ya no teníam... https://t.co/rz7hfm22mx]]></document>
		<document><![CDATA[#wg PRISA vende Media Capital a la francesa Altice - PRISA, editor de EL PAÍS, ha sucrito un contrato de venta ... https://t.co/0VEmTE5YaE]]></document>
		<document><![CDATA[#wg Octavo y último encierro de San Fermín 2017 - Los toros de la ganadería andaluza de Miuraserán los protagon... https://t.co/Zm3ZMpKHye]]></document>
		<document><![CDATA[#wg Por qué los nadadores imitan la patada de delfín - Por definición, las sirenas son criaturas mitológicas co... https://t.co/yUdp8RRNWD]]></document>
		<document><![CDATA[#wg El abuso de drogas trastoca el mercado laboral en EE UU - La principal causa de muertes en Estados Unidos e... https://t.co/mRTFk4W9Ie]]></document>
		<document><![CDATA[#wg La justicia peruana ordena la prisión de Ollanta Humala por el caso Odebrecht https://t.co/AHSPOPaBmR]]></document>
		<document><![CDATA[#wg Sistema informático de seguridad global - David Villar, gallego de 45 años, es creador y fundador de Walkir... https://t.co/jaQFqTzsYe]]></document>
		<document><![CDATA[#wg Mad Cool fue tan parco sobre la muerte de Pedro Aunión por “orden directa de la Policía” https://t.co/5DZ0XFfWOc]]></document>
		<document><![CDATA[#wg Descubierta Sarasvati, una de las mayores estructuras del universo https://t.co/8b1fLcq0K1]]></document>
		<document><![CDATA[#wg Ecuador destapa las deudas ocultas de la gestión de Correa https://t.co/m2zyilatb0]]></document>
		<document><![CDATA[#wg Rajoy acusa a Puigdemont de purgar a los dudosos de su propio partido https://t.co/AoUgWCpjSM]]></document>
		<document><![CDATA[#wg Los Reyes dejan Reino Unido con buenas sensaciones para la relación tras el Brexit https://t.co/4hjGZwDYdq]]></document>
		<document><![CDATA[#wg La inmigrante albanesa que cuidaba ancianos y triunfa como soprano https://t.co/7HuEthV1KE]]></document>
		<document><![CDATA[#wg Un camión grúa cae al agua desde los 90 metros de altura del puente Carranza, en Cádiz https://t.co/te80dZiJjX]]></document>
		<document><![CDATA[#wg Carmena incorpora 836 trabajadores más para para mejorar la limpieza https://t.co/IsonI5gywG]]></document>
		<document><![CDATA[#wg EasyJet crea una compañía en Austria para sortear el ‘Brexit’ https://t.co/FrsvwxhPq5]]></document>
		<document><![CDATA[#wg Día Nacional de Francia, en imágenes - Francia conmemora en su fiesta nacional la toma de la Bastilla de 17... https://t.co/r0yBrASbaJ]]></document>
		<document><![CDATA[#wg El Tour perdona a Urán, que recupera 20s y se queda a 35s en la general https://t.co/6aStE2WGRY]]></document>
		<document><![CDATA[#wg El recorte de gasto enfrenta a Macron con el jefe del Ejército en el 14 de julio https://t.co/EyjzKLa7Zq]]></document>
		<document><![CDATA[#wg Oriol Pujol acepta dos años y medio de prisión por el caso de las ITV https://t.co/QTvwMw8swz]]></document>
		<document><![CDATA[#wg Wimbledon 2017: cuadro, horario y resultados de los partidos https://t.co/cHhsbmfXho]]></document>
		<document><![CDATA[#wg El atentado que sembró el terror en la fiesta nacional francesa https://t.co/DpW2a2Qb7q]]></document>
		<document><![CDATA[#wg Gigi Hadid y Zayn Malik se consolidan como la pareja de moda https://t.co/T56sMn0Pek]]></document>
		<document><![CDATA[#wg Thelonious para los amigos - La primera vez que Kenny Barron grabó a dúo con otro pianista fue hace casi 40... https://t.co/nDFsSglRwn]]></document>
		<document><![CDATA[#wg Abatidos tres árabes israelíes tras herir a tiros a tres policías en Jerusalén https://t.co/tSD4xjwdbV]]></document>
		<document><![CDATA[#wg Quim Forn, el hombre tranquilo - Aunque a menor escala, Joaquim Forn (Barcelona, 1964), conoce la cartera d... https://t.co/GZ7Uaqz78d]]></document>
		<document><![CDATA[#wg Gemma Nierga se despide de los oyentes de la Cadena SER - Gemma Nierga se ha despedido este viernes de los ... https://t.co/dCAo48s8dj]]></document>
	</documents>
</author>